<?xml version="1.0" encoding="UTF-8"?><permutation name="E34E0B2FC7D1CC21F6A5EA29E0388C8E">
<variables>
<mgwt.os>iphone</mgwt.os>
<user.agent>safari</user.agent>
<mobile.user.agent>not_mobile</mobile.user.agent>
</variables>
<files>
<file>avtoduma/compilation-mappings.txt</file>
<file>index.html</file>
<file>logo.png</file>
<file>avtoduma/avtoduma.devmode.js</file>
<file>avtoduma/E34E0B2FC7D1CC21F6A5EA29E0388C8E.cache.js</file>
<file>./</file>
<file>avtoduma/avtoduma.nocache.js</file>
<file>avtoduma/clear.cache.gif</file>
</files>
</permutation>
